cidre/__init__.py
cidre/cidre.py
cidre/draw.py
cidre/filters.py
cidre/utils.py
cidre-0.0.1.dist-info/LICENSE
cidre-0.0.1.dist-info/METADATA
cidre-0.0.1.dist-info/WHEEL
cidre-0.0.1.dist-info/top_level.txt
cidre-0.0.1.dist-info/RECORD
