Metadata-Version: 2.1
Name: cidre
Version: 0.0.1
Summary: Algorithm for finding anomalous groups in networks
Home-page: https://github.com/skojaku/cidre
Author: Sadamori Kojaku
License: MIT
Keywords: networks,community detection,anomaly detection
Platform: UNKNOWN
Classifier: Development Status :: 3 - Alpha
Classifier: Intended Audience :: Science/Research
Classifier: Topic :: Software Development
Classifier: License :: OSI Approved :: MIT License
Classifier: Programming Language :: Python :: 3.7
Classifier: Programming Language :: Python :: 3.8
Classifier: Programming Language :: Python :: 3.9
License-File: LICENSE
Requires-Dist: networkx (>=2.0)
Requires-Dist: numpy (>=1.16.5)
Requires-Dist: scipy (>=1.5.2)
Requires-Dist: seaborn (>=0.11.0)
Requires-Dist: pandas (>=1.1.0)
Requires-Dist: tqdm (>=4.49.0)
Requires-Dist: matplotlib (==3.1.3)
Requires-Dist: seaborn (==0.11.1)
